{"title":"API for skill informations","pubDate":"2013-05-20T21:50:32.000Z","guid":"http://forum-en.guildwars2.com/forum/community/api/API-for-skill-informations","comments":[{"pubDate":"2013-05-20T21:50:32.000Z","guid":"http://forum-en.guildwars2.com/forum/community/api/API-for-skill-informations/2063667","author":"Varonth.5830","body":"\n<p>Is there any plan for an API which will provide up to date skill informations?</p>\n<p>Seems kinda useful, as it would allow any side to be up to date if it just grabs the current informations once per hour/day/week.</p>\n<p>(as I am still wondering if I continue my work on ‘TeamBuilder2’ it would also save quite some time for me, when I don’t have to copy&amp;paste everything).<br>\nBasically the same for skills that you have for items/recipes.</p>\n<p>That would be great<img src=\"/include/images/smilies/lion.png\"></p>","arenanet":false}]}