{"title":"Bug in Guild-Details API","pubDate":"2015-09-28T16:59:26.000Z","guid":"http://forum-en.guildwars2.com/forum/community/api/Bug-in-Guild-Details-API","comments":[{"pubDate":"2015-09-28T17:56:16.000Z","guid":"http://forum-en.guildwars2.com/forum/community/api/Bug-in-Guild-Details-API/5540460","author":"Lawton Campbell.8517","body":"\n<p>:&lt;</p>\n<p>The fix should go out with HoT; my bad.</p>","arenanet":true},{"pubDate":"2015-09-28T16:59:27.000Z","guid":"http://forum-en.guildwars2.com/forum/community/api/Bug-in-Guild-Details-API/5540233","author":"Shtra Quo.1932","body":"\n<p>If you do a vertical flip of the foreground instead of “FlipForegroundVertical” the API returns “FlipForegroundHorizontal”.</p>","arenanet":false}]}