{"title":"Increasing mouse sensivity?","pubDate":"2016-12-26T17:21:37.000Z","guid":"http://forum-en.guildwars2.com/forum/community/api/Increasing-mouse-sensivity","comments":[{"pubDate":"2016-12-26T20:21:56.000Z","guid":"http://forum-en.guildwars2.com/forum/community/api/Increasing-mouse-sensivity/6445850","author":"SlippyCheeze.5483","body":"\n<p>You should probably do this in the OS, rather than in-game. <img src=\"/include/images/smilies/smile.png\"></p>","arenanet":false},{"pubDate":"2016-12-26T17:21:37.000Z","guid":"http://forum-en.guildwars2.com/forum/community/api/Increasing-mouse-sensivity/6445687","author":"beogoat.9215","body":"\n<p>This is perhaps an old topic, but is there anyway to increase mouse sensitivity or camera rotation speed even further?</p>\n<p>My display settings are set to Windowed Fullscreen, but I doubt that should make any difference.</p>\n<p>Thanks.</p>","arenanet":false}]}