{"title":"MoS Matchups Tools","pubDate":"2013-05-20T21:05:07.000Z","guid":"http://forum-en.guildwars2.com/forum/community/api/MoS-Matchups-Tools","comments":[{"pubDate":"2013-05-22T14:10:33.000Z","guid":"http://forum-en.guildwars2.com/forum/community/api/MoS-Matchups-Tools/2073346","author":"Weris.5248","body":"\n<p>New version of the live maps page with 4 new tabs : one for each map (EB, Green, Blue and red map).<br>\nOn these tabs, the events logs display only logs related to the corresponding map :</p>\n<p><a href=\"http://mos.millenium.org/eu/matchups/map/685/eb?lang=en\">http://mos.millenium.org/eu/matchups/map/685/eb?lang=en</a></p>","arenanet":false},{"pubDate":"2013-05-20T21:33:29.000Z","guid":"http://forum-en.guildwars2.com/forum/community/api/MoS-Matchups-Tools/2063558","author":"MRA.4758","body":"\n<p>Thanks to both MoS and ANet for their effort on this. This service is awesome.</p>\n<p>~MRA</p>","arenanet":false},{"pubDate":"2013-05-20T21:31:45.000Z","guid":"http://forum-en.guildwars2.com/forum/community/api/MoS-Matchups-Tools/2063544","author":"poke.3712","body":"\n<p>That was quick, well done!</p>","arenanet":false},{"pubDate":"2013-05-20T21:05:07.000Z","guid":"http://forum-en.guildwars2.com/forum/community/api/MoS-Matchups-Tools/2063367","author":"Weris.5248","body":"\n<p>The MoS matchups tools has improved and now use this new API to display live scores and maps :</p>\n<p><a href=\"http://mos.millenium.org\">http://mos.millenium.org</a>.</p>\n<p>Thank you Cliff for this stuff.</p>","arenanet":false}]}