{"title":"Skale Venom (item id 8696) not in api","pubDate":"2015-07-14T17:11:52.000Z","guid":"http://forum-en.guildwars2.com/forum/community/api/Skale-Venom-item-id-8696-not-in-api","comments":[{"pubDate":"2015-07-14T17:20:12.000Z","guid":"http://forum-en.guildwars2.com/forum/community/api/Skale-Venom-item-id-8696-not-in-api/5282167","author":"zwei.9073","body":"\n<p>Something similar is going for itemId 39140 and Book of Rabid Deeds – <a href=\"https://wiki.guildwars2.com/wiki/Book_of_Rabid_Deeds#item2\">https://wiki.guildwars2.com/wiki/Book_of_Rabid_Deeds#item2</a></p>\n<p>And: <a href=\"https://api.guildwars2.com/v2/items/35243\">https://api.guildwars2.com/v2/items/35243</a> – <a href=\"http://wiki.guildwars2.com/wiki/Invaders_Warhorn\">http://wiki.guildwars2.com/wiki/Invaders_Warhorn</a></p>\n<p>And: <a href=\"https://api.guildwars2.com/v2/items/8702\">https://api.guildwars2.com/v2/items/8702</a> – <a href=\"https://wiki.guildwars2.com/wiki/Fire_Elemental_Powder\">https://wiki.guildwars2.com/wiki/Fire_Elemental_Powder</a></p>","arenanet":false},{"pubDate":"2015-07-14T17:11:52.000Z","guid":"http://forum-en.guildwars2.com/forum/community/api/Skale-Venom-item-id-8696-not-in-api/5282144","author":"zwei.9073","body":"\n<p>API returns error for item “Skale Venom” – <a href=\"https://api.guildwars2.com/v2/items/8696\">https://api.guildwars2.com/v2/items/8696</a></p>\n<p>But this item is definitelly in game: <a href=\"https://wiki.guildwars2.com/wiki/Skale_Venom_(consumable)\" title=\"consumable\">https://wiki.guildwars2.com/wiki/Skale_Venom_</a></p>","arenanet":false}]}